allinpy/__init__.py
allinpy/io_utils/__init__.py
allinpy/io_utils/file_utils.py
allinpy/plotting/__init__.py
allinpy/plotting/plot_utils.py
allinpy/utils/__init__.py
allinpy/utils/utilities.py
allinpy-0.2.0.dist-info/licenses/LICENSE
allinpy-0.2.0.dist-info/METADATA
allinpy-0.2.0.dist-info/WHEEL
allinpy-0.2.0.dist-info/top_level.txt
allinpy-0.2.0.dist-info/RECORD
