Metadata-Version: 2.4
Name: allinpy
Version: 0.2.0
Summary: Modular utilities for scientific computing and plotting.
Author-email: Rasmus Bruckner <rasmusb@zedat.fu-berlin.de>
License: 
Project-URL: Source, https://github.com/rasmusbruckner/allinpy
Project-URL: Documentation, https://rasmusbruckner.github.io/allinpy/
Requires-Python: >=3.10
License-File: LICENSE
Requires-Dist: numpy
Requires-Dist: pandas
Requires-Dist: matplotlib
Requires-Dist: tqdm
Dynamic: license-file
